user_agents/__init__.py
user_agents/devices.json
user_agents/parsers.py
user_agents/tests.py
slipmatio_user_agents-2025.5.1.dist-info/METADATA
slipmatio_user_agents-2025.5.1.dist-info/WHEEL
slipmatio_user_agents-2025.5.1.dist-info/licenses/AUTHORS.md
slipmatio_user_agents-2025.5.1.dist-info/licenses/LICENSE.txt
slipmatio_user_agents-2025.5.1.dist-info/RECORD
