Metadata-Version: 2.4
Name: slipmatio-user-agents
Version: 2025.5.1
Summary: A library to identify devices (phones, tablets) and their capabilities by parsing browser user agent strings.
Project-URL: Changelog, https://github.com/slipmatio/user-agents/blob/main/CHANGES.md
Project-URL: Bluesky, https://bsky.app/profile/uninen.net
Project-URL: Source, https://github.com/slipmatio/user-agents
Project-URL: Twitter, https://twitter.com/uninen
Author-email: Ville Säävuori <ville@slipmat.io>
License-File: AUTHORS.md
License-File: LICENSE.txt
Classifier: Development Status :: 5 - Production/Stable
Classifier: Environment :: Web Environment
Classifier: Intended Audience :: Developers
Classifier: License :: OSI Approved :: MIT License
Classifier: Operating System :: OS Independent
Classifier: Programming Language :: Python
Classifier: Programming Language :: Python :: 3
Classifier: Programming Language :: Python :: 3.12
Classifier: Programming Language :: Python :: 3.13
Classifier: Topic :: Internet :: WWW/HTTP
Classifier: Topic :: Software Development :: Libraries :: Python Modules
Requires-Python: >=3.12
Requires-Dist: pyyaml>=6.0.2
Requires-Dist: ua-parser>=1.0.1
